RemoteMonitorLibrary/__init__.py
RemoteMonitorLibrary/version.py
RemoteMonitorLibrary/api/__init__.py
RemoteMonitorLibrary/api/db.py
RemoteMonitorLibrary/api/model.py
RemoteMonitorLibrary/api/plugins.py
RemoteMonitorLibrary/api/services.py
RemoteMonitorLibrary/api/tools.py
RemoteMonitorLibrary/library/RemoteMonitorLibrary.html
RemoteMonitorLibrary/library/RemoteMonitorLibrary.py
RemoteMonitorLibrary/library/__init__.py
RemoteMonitorLibrary/library/bi_keywords.py
RemoteMonitorLibrary/library/connection_keywords.py
RemoteMonitorLibrary/library/listeners.py
RemoteMonitorLibrary/library/robotframework_portal_addon.py
RemoteMonitorLibrary/model/__init__.py
RemoteMonitorLibrary/model/chart_abstract.py
RemoteMonitorLibrary/model/commandunit.py
RemoteMonitorLibrary/model/configuration.py
RemoteMonitorLibrary/model/db_schema.py
RemoteMonitorLibrary/model/errors.py
RemoteMonitorLibrary/model/registry_model.py
RemoteMonitorLibrary/model/runner_model.py
RemoteMonitorLibrary/plugins_modules/__init__.py
RemoteMonitorLibrary/plugins_modules/atop_plugin.py
RemoteMonitorLibrary/plugins_modules/ssh_module.py
RemoteMonitorLibrary/plugins_modules/sshlibrary_plugin.py
RemoteMonitorLibrary/plugins_modules/time_plugin.py
RemoteMonitorLibrary/runner/__init__.py
RemoteMonitorLibrary/runner/chart_generator.py
RemoteMonitorLibrary/runner/html_writer.py
RemoteMonitorLibrary/runner/ssh_runner.py
RemoteMonitorLibrary/utils/__init__.py
RemoteMonitorLibrary/utils/asinc_scheduler.py
RemoteMonitorLibrary/utils/collections.py
RemoteMonitorLibrary/utils/cron_scheduler.py
RemoteMonitorLibrary/utils/load_modules.py
RemoteMonitorLibrary/utils/logger_extension.py
RemoteMonitorLibrary/utils/logger_helper.py
RemoteMonitorLibrary/utils/singleton.py
RemoteMonitorLibrary/utils/size.py
RemoteMonitorLibrary/utils/sql_engine.py
RemoteMonitorLibrary/utils/string_utils.py
RemoteMonitorLibrary/utils/sys_utils.py
RemoteMonitorLibrary/utils/time_utils.py
unittests/__init__.py
unittests/my_plug.py
robotframework_remote_monitor_library-2.8.6.dist-info/METADATA
robotframework_remote_monitor_library-2.8.6.dist-info/WHEEL
robotframework_remote_monitor_library-2.8.6.dist-info/top_level.txt
robotframework_remote_monitor_library-2.8.6.dist-info/RECORD
