Metadata-Version: 2.1
Name: robotframework-remote-monitor-library
Version: 2.8.6
Summary: RobotFramework extended keyword library; Allow background system monitoring; aTop, Time, SSHLibrary
Home-page: https://github.com/doguz2509/robotframework_remote_monitor_library
Author: Dmitry Oguz
Author-email: doguz2509@gmail.com
License: MIT
Platform: UNKNOWN
Classifier: Programming Language :: Python :: 3
Classifier: Framework :: Robot Framework
Classifier: Framework :: Robot Framework :: Library
Classifier: Operating System :: OS Independent
Classifier: Development Status :: 3 - Alpha
Requires-Dist: robotframework
Requires-Dist: robotframework-sshlibrary
Requires-Dist: robotbackgroundlogger (~=1.2)
Requires-Dist: matplotlib
Requires-Dist: pandas
Requires-Dist: PyYAML
Requires-Dist: schedule
